{
  "schemaVersion": "1.0.0",
  "readme": "",
  "modules": [
    {
      "kind": "javascript-module",
      "path": "src/auto-check-element.ts",
      "declarations": [
        {
          "kind": "class",
          "description": "",
          "name": "AutoCheckCompleteEvent",
          "superclass": {
            "name": "AutoCheckEvent",
            "module": "src/auto-check-element.ts"
          },
          "members": [
            {
              "kind": "field",
              "name": "detail",
              "readonly": true,
              "inheritedFrom": {
                "name": "AutoCheckEvent",
                "module": "src/auto-check-element.ts"
              }
            }
          ]
        },
        {
          "kind": "class",
          "description": "",
          "name": "AutoCheckSuccessEvent",
          "superclass": {
            "name": "AutoCheckEvent",
            "module": "src/auto-check-element.ts"
          },
          "members": [
            {
              "kind": "field",
              "name": "detail",
              "readonly": true,
              "inheritedFrom": {
                "name": "AutoCheckEvent",
                "module": "src/auto-check-element.ts"
              }
            }
          ]
        },
        {
          "kind": "class",
          "description": "",
          "name": "AutoCheckStartEvent",
          "superclass": {
            "name": "AutoCheckValidationEvent",
            "module": "src/auto-check-element.ts"
          },
          "members": [
            {
              "kind": "method",
              "name": "setValidity",
              "parameters": [
                {
                  "name": "message",
                  "type": {
                    "text": "string"
                  }
                }
              ],
              "inheritedFrom": {
                "name": "AutoCheckValidationEvent",
                "module": "src/auto-check-element.ts"
              }
            },
            {
              "kind": "field",
              "name": "detail",
              "readonly": true,
              "inheritedFrom": {
                "name": "AutoCheckEvent",
                "module": "src/auto-check-element.ts"
              }
            }
          ]
        },
        {
          "kind": "class",
          "description": "",
          "name": "AutoCheckErrorEvent",
          "superclass": {
            "name": "AutoCheckValidationEvent",
            "module": "src/auto-check-element.ts"
          },
          "members": [
            {
              "kind": "method",
              "name": "setValidity",
              "parameters": [
                {
                  "name": "message",
                  "type": {
                    "text": "string"
                  }
                }
              ],
              "inheritedFrom": {
                "name": "AutoCheckValidationEvent",
                "module": "src/auto-check-element.ts"
              }
            },
            {
              "kind": "field",
              "name": "detail",
              "readonly": true,
              "inheritedFrom": {
                "name": "AutoCheckEvent",
                "module": "src/auto-check-element.ts"
              }
            }
          ]
        },
        {
          "kind": "class",
          "description": "",
          "name": "AutoCheckSendEvent",
          "superclass": {
            "name": "AutoCheckEvent",
            "module": "src/auto-check-element.ts"
          },
          "members": [
            {
              "kind": "field",
              "name": "detail",
              "readonly": true,
              "inheritedFrom": {
                "name": "AutoCheckEvent",
                "module": "src/auto-check-element.ts"
              }
            }
          ]
        },
        {
          "kind": "class",
          "description": "",
          "name": "AutoCheckElement",
          "members": [
            {
              "kind": "method",
              "name": "define",
              "static": true,
              "parameters": [
                {
                  "name": "tag",
                  "default": "'auto-check'"
                },
                {
                  "name": "registry",
                  "default": "customElements"
                }
              ]
            },
            {
              "kind": "field",
              "name": "#onloadend",
              "privacy": "private",
              "type": {
                "text": "((event: Event) => void) | null"
              },
              "default": "null"
            },
            {
              "kind": "field",
              "name": "onloadend"
            },
            {
              "kind": "field",
              "name": "input",
              "type": {
                "text": "HTMLInputElement | null"
              },
              "readonly": true
            },
            {
              "kind": "field",
              "name": "src",
              "type": {
                "text": "string"
              }
            },
            {
              "kind": "field",
              "name": "csrf",
              "type": {
                "text": "string"
              }
            },
            {
              "kind": "field",
              "name": "required",
              "type": {
                "text": "boolean"
              }
            },
            {
              "kind": "field",
              "name": "csrfField",
              "type": {
                "text": "string"
              }
            }
          ],
          "attributes": [
            {
              "name": "required"
            }
          ],
          "superclass": {
            "name": "HTMLElement"
          },
          "customElement": true
        }
      ],
      "exports": [
        {
          "kind": "js",
          "name": "AutoCheckCompleteEvent",
          "declaration": {
            "name": "AutoCheckCompleteEvent",
            "module": "src/auto-check-element.ts"
          }
        },
        {
          "kind": "js",
          "name": "AutoCheckSuccessEvent",
          "declaration": {
            "name": "AutoCheckSuccessEvent",
            "module": "src/auto-check-element.ts"
          }
        },
        {
          "kind": "js",
          "name": "AutoCheckStartEvent",
          "declaration": {
            "name": "AutoCheckStartEvent",
            "module": "src/auto-check-element.ts"
          }
        },
        {
          "kind": "js",
          "name": "AutoCheckErrorEvent",
          "declaration": {
            "name": "AutoCheckErrorEvent",
            "module": "src/auto-check-element.ts"
          }
        },
        {
          "kind": "js",
          "name": "AutoCheckSendEvent",
          "declaration": {
            "name": "AutoCheckSendEvent",
            "module": "src/auto-check-element.ts"
          }
        },
        {
          "kind": "js",
          "name": "AutoCheckElement",
          "declaration": {
            "name": "AutoCheckElement",
            "module": "src/auto-check-element.ts"
          }
        },
        {
          "kind": "js",
          "name": "default",
          "declaration": {
            "name": "AutoCheckElement",
            "module": "src/auto-check-element.ts"
          }
        }
      ]
    }
  ]
}
